{
  "project_info": {
    "project_number": "219558347225",
    "firebase_url": "https://foodsavior-37471.firebaseio.com",
    "project_id": "foodsavior-37471",
    "storage_bucket": "foodsavior-37471.appspot.com"
  },
  "client": [
    {
      "client_info": {
        "mobilesdk_app_id": "1:219558347225:android:381ba3e973187c34",
        "android_client_info": {
          "package_name": "com.example.ellyn.assignment"
        }
      },
      "oauth_client": [
        {
          "client_id": "219558347225-fi85s0qt48j0ugpennrjbm678t9dnln0.apps.googleusercontent.com",
          "client_type": 3
        }
      ],
      "api_key": [
        {
          "current_key": "AIzaSyCVjBZ-k_swid8zfnVRtgmuBn6unFpxHdQ"
        }
      ],
      "services": {
        "analytics_service": {
          "status": 1
        },
        "appinvite_service": {
          "status": 1,
          "other_platform_oauth_client": []
        },
        "ads_service": {
          "status": 2
        }
      }
    }
  ],
  "configuration_version": "1"
}